README.rst
setup.py
mysql_stream.egg-info/PKG-INFO
mysql_stream.egg-info/SOURCES.txt
mysql_stream.egg-info/dependency_links.txt
mysql_stream.egg-info/requires.txt
mysql_stream.egg-info/top_level.txt
mysqlstream/__init__.py
mysqlstream/en_decoder.py
mysqlstream/field_type.py
mysqlstream/models.py
mysqlstream/mysql_db_pool.py
mysqlstream/mysql_executor.py
mysqlstream/tests/__init__.py
mysqlstream/tests/client_demo.py
mysqlstream/tests/orm_demo.py
mysqlstream/tests/test_config.py
mysqlstream/tests/test_models.py
mysqlstream/tests/test_mysql_db_pool.py
mysqlstream/tests/test_mysql_executor.py