Metadata-Version: 1.0
Name: mysql-stream
Version: 0.0.4
Summary: simple and easy to use MySQL client and ORM library
Home-page: https://github.com/streamDream/mysql-stream
Author: chenchong
Author-email: boy3565@163.com
License: UNKNOWN
Keywords: mysql,client,orm
Platform: UNKNOWN
